pymysql/__init__.py
pymysql/_auth.py
pymysql/charset.py
pymysql/connections.py
pymysql/converters.py
pymysql/cursors.py
pymysql/err.py
pymysql/optionfile.py
pymysql/protocol.py
pymysql/times.py
pymysql/constants/CLIENT.py
pymysql/constants/COMMAND.py
pymysql/constants/CR.py
pymysql/constants/ER.py
pymysql/constants/FIELD_TYPE.py
pymysql/constants/FLAG.py
pymysql/constants/SERVER_STATUS.py
pymysql/constants/__init__.py
PyMySQL-1.0.3.dist-info/LICENSE
PyMySQL-1.0.3.dist-info/METADATA
PyMySQL-1.0.3.dist-info/WHEEL
PyMySQL-1.0.3.dist-info/top_level.txt
PyMySQL-1.0.3.dist-info/RECORD
