Metadata-Version: 2.1
Name: PyMySQL
Version: 1.0.3
Summary: Pure Python MySQL Driver
Author-email: Inada Naoki <songofacandy@gmail.com>, Yutaka Matsubara <yutaka.matsubara@gmail.com>
License: MIT License
Project-URL: Project, https://github.com/PyMySQL/PyMySQL
Project-URL: Documentation, https://pymysql.readthedocs.io/
Keywords: MySQL
Classifier: Development Status :: 5 - Production/Stable
Classifier: Programming Language :: Python :: 3
Classifier: Programming Language :: Python :: 3.7
Classifier: Programming Language :: Python :: 3.8
Classifier: Programming Language :: Python :: 3.9
Classifier: Programming Language :: Python :: 3.10
Classifier: Programming Language :: Python :: 3.11
Classifier: Programming Language :: Python :: Implementation :: CPython
Classifier: Programming Language :: Python :: Implementation :: PyPy
Classifier: Intended Audience :: Developers
Classifier: License :: OSI Approved :: MIT License
Classifier: Topic :: Database
Requires-Python: >=3.7
Provides-Extra: rsa
Provides-Extra: ed25519
License-File: LICENSE
